micropython_lis3dh/__init__.py
micropython_lis3dh/i2c_helpers.py
micropython_lis3dh/lis3dh.py
micropython_lis3dh-0.1.2.dist-info/LICENSE
micropython_lis3dh-0.1.2.dist-info/METADATA
micropython_lis3dh-0.1.2.dist-info/WHEEL
micropython_lis3dh-0.1.2.dist-info/top_level.txt
micropython_lis3dh-0.1.2.dist-info/RECORD
