Metadata-Version: 2.1
Name: micropython-lis3dh
Version: 0.1.2
Summary: LIS3DH MicroPython Driver
Author-email: "Jose D. Montoya" <lis3dh@mailmeto.mozmail.com>
License: MIT
Project-URL: Homepage, https://github.com/jposada202020/MicroPython_LIS3DH
Keywords: micropython,lis3dh,sernsor,acceleration,tap,movement,sensor
Classifier: Intended Audience :: Developers
Classifier: Topic :: Software Development :: Libraries
Classifier: Topic :: Software Development :: Embedded Systems
Classifier: Topic :: System :: Hardware
Classifier: License :: OSI Approved :: MIT License
Classifier: Programming Language :: Python :: Implementation :: MicroPython
License-File: LICENSE
